deepfocus/__init__.py
deepfocus/download_utils.py
deepfocus/fasttext_embs.py
deepfocus/focus.py
deepfocus/logger.py
deepfocus/vocab_helper.py
deepfocus-1.0.1.dist-info/LICENSE
deepfocus-1.0.1.dist-info/METADATA
deepfocus-1.0.1.dist-info/WHEEL
deepfocus-1.0.1.dist-info/top_level.txt
deepfocus-1.0.1.dist-info/zip-safe
deepfocus-1.0.1.dist-info/RECORD
