Metadata-Version: 2.1
Name: deepfocus
Version: 1.0.1
Summary: Offcial Python implementation of "FOCUS: Effective Embedding Initialization for Monolingual Specialization of Multilingual Models" published at EMNLP 2023.
Home-page: https://github.com/konstantinjdobler/focus
Project-URL: Bug Tracker, https://github.com/konstantinjdobler/focus/issues
Project-URL: Changelog, https://github.com/konstantinjdobler/focus/releases
Classifier: Programming Language :: Python :: 3
Classifier: License :: OSI Approved :: Apache Software License
Classifier: Intended Audience :: Developers
Requires-Python: >=3.8
License-File: LICENSE
Requires-Dist: torch
Requires-Dist: transformers >=4.0.0
Requires-Dist: datasets
Requires-Dist: entmax
Requires-Dist: fasttext
Requires-Dist: fastdist
Requires-Dist: requests
Requires-Dist: numpy
Requires-Dist: numba
Requires-Dist: scipy
Requires-Dist: tqdm
Requires-Dist: print-on-steroids
Provides-Extra: dev
Requires-Dist: black ; extra == 'dev'
Requires-Dist: ruff ; extra == 'dev'
Requires-Dist: pytest ; extra == 'dev'
Requires-Dist: pytest-mock ; extra == 'dev'
